grizzly/__init__.py
grizzly/__version__.py
grizzly/behave.py
grizzly/context.py
grizzly/exceptions.py
grizzly/gevent.py
grizzly/locust.py
grizzly/log.py
grizzly/py.typed
grizzly/auth/__init__.py
grizzly/auth/aad.py
grizzly/events/__init__.py
grizzly/events/request_logger.py
grizzly/events/response_handler.py
grizzly/listeners/__init__.py
grizzly/listeners/influxdb.py
grizzly/scenarios/__init__.py
grizzly/scenarios/iterator.py
grizzly/steps/__init__.py
grizzly/steps/_helpers.py
grizzly/steps/setup.py
grizzly/steps/utils.py
grizzly/steps/background/__init__.py
grizzly/steps/background/setup.py
grizzly/steps/background/shapes.py
grizzly/steps/scenario/__init__.py
grizzly/steps/scenario/response.py
grizzly/steps/scenario/results.py
grizzly/steps/scenario/setup.py
grizzly/steps/scenario/user.py
grizzly/steps/scenario/tasks/__init__.py
grizzly/steps/scenario/tasks/async_group.py
grizzly/steps/scenario/tasks/async_timer.py
grizzly/steps/scenario/tasks/clients.py
grizzly/steps/scenario/tasks/conditional.py
grizzly/steps/scenario/tasks/date.py
grizzly/steps/scenario/tasks/keystore.py
grizzly/steps/scenario/tasks/log_message.py
grizzly/steps/scenario/tasks/loop.py
grizzly/steps/scenario/tasks/request.py
grizzly/steps/scenario/tasks/transformer.py
grizzly/steps/scenario/tasks/until.py
grizzly/steps/scenario/tasks/wait_between.py
grizzly/steps/scenario/tasks/wait_explicit.py
grizzly/steps/scenario/tasks/write_file.py
grizzly/tasks/__init__.py
grizzly/tasks/async_group.py
grizzly/tasks/async_timer.py
grizzly/tasks/conditional.py
grizzly/tasks/date.py
grizzly/tasks/keystore.py
grizzly/tasks/log_message.py
grizzly/tasks/loop.py
grizzly/tasks/request.py
grizzly/tasks/set_variable.py
grizzly/tasks/transformer.py
grizzly/tasks/until.py
grizzly/tasks/wait_between.py
grizzly/tasks/wait_explicit.py
grizzly/tasks/write_file.py
grizzly/tasks/clients/__init__.py
grizzly/tasks/clients/blobstorage.py
grizzly/tasks/clients/http.py
grizzly/tasks/clients/messagequeue.py
grizzly_loadtester-3.2.6.dist-info/METADATA
grizzly_loadtester-3.2.6.dist-info/WHEEL
grizzly_loadtester-3.2.6.dist-info/RECORD
