Metadata-Version: 2.4
Name: grizzly-loadtester
Version: 3.2.6
Summary: Traffic generator based on locust and behave
Project-URL: Documentation, https://biometria-se.github.io/grizzly/framework
Project-URL: Code, https://github.com/biometria-se/grizzly/
Project-URL: Tracker, https://github.com/Biometria-se/grizzly/issues
Author-email: biometria <opensource@biometria.se>
Maintainer-email: Mikael Göransson <github@mgor.se>
License-Expression: MIT
Keywords: behave,load,loadtest,locust,performance,traffic generator
Classifier: Development Status :: 4 - Beta
Classifier: License :: OSI Approved :: MIT License
Classifier: Natural Language :: English
Classifier: Programming Language :: Python
Classifier: Programming Language :: Python :: 3 :: Only
Classifier: Programming Language :: Python :: 3.10
Classifier: Programming Language :: Python :: 3.11
Classifier: Programming Language :: Python :: 3.12
Classifier: Programming Language :: Python :: 3.13
Classifier: Programming Language :: Python :: Implementation :: CPython
Requires-Python: >=3.10
Requires-Dist: azure-iot-device>=2.14.0
Requires-Dist: azure-storage-blob>=12.26.0
Requires-Dist: grizzly-loadtester-common
Requires-Dist: grizzly-loadtester-extras-async-messaged
Requires-Dist: influxdb-client>=1.49.0
Requires-Dist: influxdb>=5.3.2
Requires-Dist: locust==2.40.2
Requires-Dist: roundrobin>=0.0.4
Provides-Extra: mq
Requires-Dist: grizzly-loadtester-extras-async-messaged[mq]; extra == 'mq'
